kvpress/__init__.py
kvpress/attention_patch.py
kvpress/pipeline.py
kvpress/utils.py
kvpress/presses/__init__.py
kvpress/presses/adakv_press.py
kvpress/presses/base_press.py
kvpress/presses/block_press.py
kvpress/presses/chunk_press.py
kvpress/presses/chunkkv_press.py
kvpress/presses/compactor_press.py
kvpress/presses/composed_press.py
kvpress/presses/criticalkv_press.py
kvpress/presses/cur_press.py
kvpress/presses/decoding_press.py
kvpress/presses/duo_attention_press.py
kvpress/presses/expected_attention_press.py
kvpress/presses/expected_attention_with_stats.py
kvpress/presses/finch_press.py
kvpress/presses/key_rerotation_press.py
kvpress/presses/keydiff_press.py
kvpress/presses/knorm_press.py
kvpress/presses/kvzap_press.py
kvpress/presses/kvzip_press.py
kvpress/presses/lagkv_press.py
kvpress/presses/leverage_press.py
kvpress/presses/non_causal_attention_press.py
kvpress/presses/observed_attention_press.py
kvpress/presses/per_layer_compression_press.py
kvpress/presses/prefill_decoding_press.py
kvpress/presses/pyramidkv_press.py
kvpress/presses/qfilter_press.py
kvpress/presses/random_press.py
kvpress/presses/scorer_press.py
kvpress/presses/simlayerkv_press.py
kvpress/presses/snapkv_press.py
kvpress/presses/streaming_llm_press.py
kvpress/presses/think_press.py
kvpress/presses/threshold_press.py
kvpress/presses/tova_press.py
kvpress-0.4.1.dist-info/METADATA
kvpress-0.4.1.dist-info/WHEEL
kvpress-0.4.1.dist-info/licenses/LICENSE
kvpress-0.4.1.dist-info/RECORD
