Metadata-Version: 2.4
Name: kvpress
Version: 0.4.1
Summary: Efficiently compress the KV cache of any pretrained transformer
Author: Simon Jegou, Maximilian Jeblick, Alessio Devoto, David Austin
License-File: LICENSE
Requires-Python: >=3.10
Requires-Dist: accelerate<2,>=1.0.0
Requires-Dist: cachetools<6,>=5.5.2
Requires-Dist: datasets<3,>=2.21.0
Requires-Dist: fire<0.7,>=0.6.0
Requires-Dist: numpy<3,>=2.0.0
Requires-Dist: pandas<3,>=2.2.2
Requires-Dist: protobuf<6,>=5.27.2
Requires-Dist: requests<3,>=2.32.3
Requires-Dist: sentencepiece<0.3,>=0.2.0
Requires-Dist: torch<3,>=2.3.1
Requires-Dist: transformers>=4.56
Provides-Extra: eval
Requires-Dist: bert-score<0.4,>=0.3.13; extra == 'eval'
Requires-Dist: nltk<4,>=3.9.1; extra == 'eval'
Requires-Dist: rouge<2,>=1.0.1; extra == 'eval'
Requires-Dist: scipy<2,>=1.13.1; extra == 'eval'
Requires-Dist: tqdm<5,>=4.66.4; extra == 'eval'
Provides-Extra: flash-attn
Requires-Dist: flash-attn; extra == 'flash-attn'
